LICENSE.txt
MANIFEST.in
README.rst
VERSION.txt
requirements.txt
setup.py
von_anchor/__init__.py
von_anchor/cache.py
von_anchor/canon.py
von_anchor/error.py
von_anchor/frill.py
von_anchor/indytween.py
von_anchor/tails.py
von_anchor/util.py
von_anchor/validcfg.py
von_anchor.egg-info/PKG-INFO
von_anchor.egg-info/SOURCES.txt
von_anchor.egg-info/dependency_links.txt
von_anchor.egg-info/entry_points.txt
von_anchor.egg-info/requires.txt
von_anchor.egg-info/top_level.txt
von_anchor/a2a/__init__.py
von_anchor/a2a/diddoc.py
von_anchor/a2a/docutil.py
von_anchor/a2a/publickey.py
von_anchor/a2a/service.py
von_anchor/anchor/.base.py.swp
von_anchor/anchor/__init__.py
von_anchor/anchor/base.py
von_anchor/anchor/demo.py
von_anchor/anchor/holderprover.py
von_anchor/anchor/issuer.py
von_anchor/anchor/origin.py
von_anchor/anchor/rrbuilder.py
von_anchor/anchor/smith.py
von_anchor/anchor/verifier.py
von_anchor/nodepool/__init__.py
von_anchor/nodepool/manager.py
von_anchor/nodepool/nodepool.py
von_anchor/nodepool/protocol.py
von_anchor/op/__init__.py
von_anchor/op/setnym.py
von_anchor/wallet/__init__.py
von_anchor/wallet/info.py
von_anchor/wallet/manager.py
von_anchor/wallet/record.py
von_anchor/wallet/search.py
von_anchor/wallet/wallet.py