Metadata-Version: 1.2
Name: von-anchor
Version: 1.11.2
Summary: VON anchors
Home-page: https://github.com/PSPC-SPAC-buyandsell/von_anchor
Author: PSPS-SPAC
Author-email: stephen.klump@becker-carroll.com
License: Apache Software License
Download-URL: https://github.com/PSPC-SPAC-buyandsell/von_anchor/archive/1.11.2.tar.gz
Keywords: VON,SRI,anchor,The Org Book,indy
Platform: UNKNOWN
Classifier: Development Status :: 3 - Alpha
Classifier: Intended Audience :: Developers
Classifier: Topic :: Software Development
Classifier: License :: OSI Approved :: Apache Software License
Classifier: Programming Language :: Python :: 3.5
Requires-Python: >=3.5
